compose_farm/__init__.py
compose_farm/_version.py
compose_farm/compose.py
compose_farm/config.py
compose_farm/console.py
compose_farm/example-config.yaml
compose_farm/executor.py
compose_farm/glances.py
compose_farm/logs.py
compose_farm/operations.py
compose_farm/paths.py
compose_farm/py.typed
compose_farm/registry.py
compose_farm/ssh_keys.py
compose_farm/state.py
compose_farm/traefik.py
compose_farm/cli/__init__.py
compose_farm/cli/app.py
compose_farm/cli/common.py
compose_farm/cli/config.py
compose_farm/cli/lifecycle.py
compose_farm/cli/management.py
compose_farm/cli/monitoring.py
compose_farm/cli/ssh.py
compose_farm/cli/web.py
compose_farm/web/__init__.py
compose_farm/web/app.py
compose_farm/web/cdn.py
compose_farm/web/deps.py
compose_farm/web/streaming.py
compose_farm/web/vendor-assets.json
compose_farm/web/ws.py
compose_farm/web/routes/__init__.py
compose_farm/web/routes/actions.py
compose_farm/web/routes/api.py
compose_farm/web/routes/containers.py
compose_farm/web/routes/pages.py
compose_farm/web/static/app.css
compose_farm/web/static/app.js
compose_farm/web/templates/console.html
compose_farm/web/templates/containers.html
compose_farm/web/templates/index.html
compose_farm/web/templates/stack.html
compose_farm/web/templates/partials/command_palette.html
compose_farm/web/templates/partials/components.html
compose_farm/web/templates/partials/config_error.html
compose_farm/web/templates/partials/containers.html
compose_farm/web/templates/partials/glances.html
compose_farm/web/templates/partials/icons.html
compose_farm/web/templates/partials/pending.html
compose_farm/web/templates/partials/sidebar.html
compose_farm/web/templates/partials/stacks_by_host.html
compose_farm/web/templates/partials/stats.html
compose_farm/web/templates/partials/terminal.html
compose_farm/web/static/vendor/LICENSES.txt
compose_farm/web/static/vendor/daisyui-themes.css
compose_farm/web/static/vendor/daisyui.css
compose_farm/web/static/vendor/htmx.js
compose_farm-1.18.2.dist-info/METADATA
compose_farm-1.18.2.dist-info/WHEEL
compose_farm-1.18.2.dist-info/entry_points.txt
compose_farm-1.18.2.dist-info/licenses/LICENSE
compose_farm-1.18.2.dist-info/RECORD
