Metadata-Version: 2.4
Name: compose-farm
Version: 1.18.2
Summary: Compose Farm - run docker compose commands across multiple hosts
Project-URL: Homepage, https://github.com/basnijholt/compose-farm
Project-URL: Repository, https://github.com/basnijholt/compose-farm
Project-URL: Documentation, https://github.com/basnijholt/compose-farm#readme
Project-URL: Issues, https://github.com/basnijholt/compose-farm/issues
Project-URL: Changelog, https://github.com/basnijholt/compose-farm/releases
Author-email: Bas Nijholt <bas@nijho.lt>
Maintainer-email: Bas Nijholt <bas@nijho.lt>
License-Expression: MIT
License-File: LICENSE
Keywords: container,deployment,devops,docker,docker-compose,homelab,multi-host,orchestration,self-hosted,ssh
Classifier: Development Status :: 4 - Beta
Classifier: Environment :: Console
Classifier: Intended Audience :: Developers
Classifier: Intended Audience :: System Administrators
Classifier: License :: OSI Approved :: MIT License
Classifier: Operating System :: MacOS
Classifier: Operating System :: POSIX :: Linux
Classifier: Programming Language :: Python :: 3
Classifier: Programming Language :: Python :: 3.11
Classifier: Programming Language :: Python :: 3.12
Classifier: Programming Language :: Python :: 3.13
Classifier: Programming Language :: Python :: 3.14
Classifier: Topic :: System :: Systems Administration
Classifier: Topic :: Utilities
Classifier: Typing :: Typed
Requires-Python: >=3.11
Requires-Dist: asyncssh>=2.14.0
Requires-Dist: pydantic>=2.0.0
Requires-Dist: python-dotenv>=1.0.0
Requires-Dist: pyyaml>=6.0
Requires-Dist: rich>=13.0.0
Requires-Dist: typer>=0.9.0
Provides-Extra: web
Requires-Dist: fastapi[standard]>=0.109.0; extra == 'web'
Requires-Dist: humanize>=4.0.0; extra == 'web'
Requires-Dist: jinja2>=3.1.0; extra == 'web'
Requires-Dist: websockets>=12.0; extra == 'web'
